<annotation>
	<folder></folder>
	<filename>MONA-MAHMOUD-HASAN-MOHAMED-SHAABAN--9-_jpg.rf.4d91e048c2fb225005aa1ec717998d7f.jpg</filename>
	<path>MONA-MAHMOUD-HASAN-MOHAMED-SHAABAN--9-_jpg.rf.4d91e048c2fb225005aa1ec717998d7f.jpg</path>
	<source>
		<database>roboflow.com</database>
	</source>
	<size>
		<width>416</width>
		<height>416</height>
		<depth>3</depth>
	</size>
	<segmented>0</segmented>
	<object>
		<name>Disc Bulgerotation</name>
		<pose>Unspecified</pose>
		<truncated>0</truncated>
		<difficult>0</difficult>
		<occluded>0</occluded>
		<bndbox>
			<xmin>153</xmin>
			<xmax>197</xmax>
			<ymin>213</ymin>
			<ymax>239</ymax>
		</bndbox>
	</object>
	<object>
		<name>Degenerative Disc Diseaserotation</name>
		<pose>Unspecified</pose>
		<truncated>0</truncated>
		<difficult>0</difficult>
		<occluded>0</occluded>
		<bndbox>
			<xmin>157</xmin>
			<xmax>195</xmax>
			<ymin>254</ymin>
			<ymax>277</ymax>
		</bndbox>
	</object>
	<object>
		<name>Disc Bulgerotation</name>
		<pose>Unspecified</pose>
		<truncated>0</truncated>
		<difficult>0</difficult>
		<occluded>0</occluded>
		<bndbox>
			<xmin>166</xmin>
			<xmax>203</xmax>
			<ymin>292</ymin>
			<ymax>316</ymax>
		</bndbox>
	</object>
	<object>
		<name>Disc Bulgerotation</name>
		<pose>Unspecified</pose>
		<truncated>0</truncated>
		<difficult>0</difficult>
		<occluded>0</occluded>
		<bndbox>
			<xmin>167</xmin>
			<xmax>206</xmax>
			<ymin>134</ymin>
			<ymax>154</ymax>
		</bndbox>
	</object>
	<object>
		<name>Disc Bulgerotation</name>
		<pose>Unspecified</pose>
		<truncated>0</truncated>
		<difficult>0</difficult>
		<occluded>0</occluded>
		<bndbox>
			<xmin>159</xmin>
			<xmax>202</xmax>
			<ymin>173</ymin>
			<ymax>194</ymax>
		</bndbox>
	</object>
	<object>
		<name>Disc Bulgerotation</name>
		<pose>Unspecified</pose>
		<truncated>0</truncated>
		<difficult>0</difficult>
		<occluded>0</occluded>
		<bndbox>
			<xmin>157</xmin>
			<xmax>195</xmax>
			<ymin>255</ymin>
			<ymax>278</ymax>
		</bndbox>
	</object>
</annotation>
